pymeetups
