Metadata-Version: 1.1
Name: pymeetups
Version: 1.1.2
Summary: Find information about future Pycon conferences and meetups through your terminal
Home-page: https://github.com/waseem18/pymeetups
Author: Wasim Thabraze
Author-email: wasim@thabraze.me
License: MIT
Keywords: pymeetups
Platform: UNKNOWN
Classifier: Development Status :: 3 - Alpha
Classifier: Topic :: Utilities
Classifier: License :: OSI Approved :: MIT License
Classifier: Programming Language :: Python :: 3.5
